{
   "html_attributions" : [],
   "results" : [
      {
         "geometry" : {
            "location" : {
               "lat" : 53.44908539999999,
               "lng" : -113.5154856
            },
            "viewport" : {
               "northeast" : {
                  "lat" : 53.4504325802915,
                  "lng" : -113.5141391697085
               },
               "southwest" : {
                  "lat" : 53.44773461970851,
                  "lng" : -113.5168371302915
               }
            }
         },
         "icon" : "https://maps.gstatic.com/mapfiles/place_api/icons/shopping-71.png",
         "id" : "5b2a9c72537eb14ccc590868a75f4cdbc64d319f",
         "name" : "7-Eleven",
         "opening_hours" : {
            "open_now" : true
         },
         "photos" : [
            {
               "height" : 3024,
               "html_attributions" : [
                  "\u003ca href=\"https://maps.google.com/maps/contrib/113065838593093330571\"\u003eEdmonton News Ren TV\u003c/a\u003e"
               ],
               "photo_reference" : "CmRaAAAAq3uH9c3Gf-es9wX1VSe-UiGpFSNDzgT-V_zBYIpgcIfldthaf3N04c6illSZ0lDs9gOE3owMP7Fk-eHv3kl8xXXj-EktdUPkVm_tthQr2qWwjp9yA6flc246f4Db0UYoEhDDLXiEmkoIEVVBc1k3Ns4YGhQ7XxUTzN9HKVqtqVUxfxrr9419Rw",
               "width" : 4032
            }
         ],
         "place_id" : "ChIJ8dtZ5foeoFMRsV2OnuDgdiY",
         "plus_code" : {
            "compound_code" : "CFXM+JR Edmonton, Alberta, Canada",
            "global_code" : "9558CFXM+JR"
         },
         "rating" : 4,
         "reference" : "ChIJ8dtZ5foeoFMRsV2OnuDgdiY",
         "scope" : "GOOGLE",
         "types" : [
            "convenience_store",
            "gas_station",
            "food",
            "point_of_interest",
            "store",
            "establishment"
         ],
         "user_ratings_total" : 19,
         "vicinity" : "1903 111 Street Northwest, Edmonton"
      },
      {
         "geometry" : {
            "location" : {
               "lat" : 53.4397316,
               "lng" : -113.5192898
            },
            "viewport" : {
               "northeast" : {
                  "lat" : 53.4410888302915,
                  "lng" : -113.5174803697085
               },
               "southwest" : {
                  "lat" : 53.4383908697085,
                  "lng" : -113.5201783302915
               }
            }
         },
         "icon" : "https://maps.gstatic.com/mapfiles/place_api/icons/shopping-71.png",
         "id" : "7e907b9f0d3060bd886f5c36a27ff6539d2dd96e",
         "name" : "7-Eleven",
         "opening_hours" : {
            "open_now" : true
         },
         "photos" : [
            {
               "height" : 3144,
               "html_attributions" : [
                  "\u003ca href=\"https://maps.google.com/maps/contrib/101105742893690459538\"\u003e7-Eleven\u003c/a\u003e"
               ],
               "photo_reference" : "CmRaAAAAiGDEYzSOwGoapar6uhihgrLMe8ho4K5nLh3BuGcOL6xve9OZmcuVKY0Utxeoen9lavMF7Pufe1z0L_Zp4zVRsoy3QPmH-x55z67-SzV_NYUHoW1pf-yfoPqsqsHGY3NSEhB7GpsnAPj4rPRIWFNXCC21GhQKM7zymZxqhWQeiYZPhRTZEHvTkQ",
               "width" : 3144
            }
         ],
         "place_id" : "ChIJ62zV0fUeoFMRwwQ_tcGJuxU",
         "plus_code" : {
            "compound_code" : "CFQJ+V7 Edmonton, Alberta, Canada",
            "global_code" : "9558CFQJ+V7"
         },
         "rating" : 4.1,
         "reference" : "ChIJ62zV0fUeoFMRwwQ_tcGJuxU",
         "scope" : "GOOGLE",
         "types" : [
            "convenience_store",
            "gas_station",
            "food",
            "point_of_interest",
            "store",
            "establishment"
         ],
         "user_ratings_total" : 7,
         "vicinity" : "906 111 Street Northwest, Edmonton"
      },
      {
         "geometry" : {
            "location" : {
               "lat" : 53.4241391,
               "lng" : -113.5175396
            },
            "viewport" : {
               "northeast" : {
                  "lat" : 53.4255649802915,
                  "lng" : -113.5161717697085
               },
               "southwest" : {
                  "lat" : 53.4228670197085,
                  "lng" : -113.5188697302915
               }
            }
         },
         "icon" : "https://maps.gstatic.com/mapfiles/place_api/icons/shopping-71.png",
         "id" : "3572d8e2d03d34e42dc9988d52881cd252391dcd",
         "name" : "7-Eleven",
         "opening_hours" : {
            "open_now" : true
         },
         "photos" : [
            {
               "height" : 3144,
               "html_attributions" : [
                  "\u003ca href=\"https://maps.google.com/maps/contrib/115213303279155703932\"\u003e7-Eleven\u003c/a\u003e"
               ],
               "photo_reference" : "CmRaAAAAfS2t84nrTNRNRj5sMFDNoHQVtnrolPK4Hr8IIDP-3jZEBFjg9tQgF8z7bStrmCBGBda78FWxnOXJCdY8QhUDyeSFQyIwtCMGIw77XXUq-kDP4699Avptz04lDEHNoCIIEhAFfB6X3TwmaOCvxzNFBpCFGhR6EAWqjrCOm6Jrx-gneROmYEQKeg",
               "width" : 3144
            }
         ],
         "place_id" : "ChIJTx6iUGMeoFMR52OeYv9sGqY",
         "plus_code" : {
            "compound_code" : "CFFJ+MX Edmonton, Alberta, Canada",
            "global_code" : "9558CFFJ+MX"
         },
         "rating" : 1.9,
         "reference" : "ChIJTx6iUGMeoFMR52OeYv9sGqY",
         "scope" : "GOOGLE",
         "types" : [
            "convenience_store",
            "gas_station",
            "food",
            "point_of_interest",
            "store",
            "establishment"
         ],
         "user_ratings_total" : 8,
         "vicinity" : "11103 Ellerslie Road Southwest, Edmonton"
      },
      {
         "geometry" : {
            "location" : {
               "lat" : 53.439732,
               "lng" : -113.519024
            },
            "viewport" : {
               "northeast" : {
                  "lat" : 53.44108688029149,
                  "lng" : -113.5173473697085
               },
               "southwest" : {
                  "lat" : 53.43838891970849,
                  "lng" : -113.5200453302915
               }
            }
         },
         "icon" : "https://maps.gstatic.com/mapfiles/place_api/icons/gas_station-71.png",
         "id" : "9cbef8c91069ba2ad76361de72d0299928397912",
         "name" : "ESSO 7-Eleven 37834",
         "opening_hours" : {
            "open_now" : true
         },
         "photos" : [
            {
               "height" : 4608,
               "html_attributions" : [
                  "\u003ca href=\"https://maps.google.com/maps/contrib/102325419731742580518\"\u003eFerdinand Aguillon\u003c/a\u003e"
               ],
               "photo_reference" : "CmRaAAAA19A8rqOQlYFnJY9K6KFDV0fFrR2mJg5PhWrceOpCzK8dhe4rW4IY_WwtaEhgDY-JtuSVst7k3X19HfMFSsg5UIPh7vc5EP_XN3RJm-40qlQWtx4-Hdzclv_I_1EtivDiEhB3ETVGkWPXMsCUrV3MwgeqGhTOZc87GaI_VzFWI3K4lUw39WRBvA",
               "width" : 3456
            }
         ],
         "place_id" : "ChIJ62zV0fUeoFMR7hlu1EIDhWM",
         "plus_code" : {
            "compound_code" : "CFQJ+V9 Edmonton, Alberta, Canada",
            "global_code" : "9558CFQJ+V9"
         },
         "rating" : 3.9,
         "reference" : "ChIJ62zV0fUeoFMR7hlu1EIDhWM",
         "scope" : "GOOGLE",
         "types" : [ "gas_station", "point_of_interest", "establishment" ],
         "user_ratings_total" : 79,
         "vicinity" : "906 111 Street Northwest, Edmonton"
      },
      {
         "geometry" : {
            "location" : {
               "lat" : 53.43980000000001,
               "lng" : -113.51872
            },
            "viewport" : {
               "northeast" : {
                  "lat" : 53.4411520802915,
                  "lng" : -113.5171969697085
               },
               "southwest" : {
                  "lat" : 53.4384541197085,
                  "lng" : -113.5198949302915
               }
            }
         },
         "icon" : "https://maps.gstatic.com/mapfiles/place_api/icons/gas_station-71.png",
         "id" : "ea2e54b092aa526034690a7aa3b2a00456cba9cc",
         "name" : "Esso",
         "place_id" : "ChIJdcPzzfUeoFMRI9nmSKRBlvM",
         "plus_code" : {
            "compound_code" : "CFQJ+WG Edmonton, Alberta, Canada",
            "global_code" : "9558CFQJ+WG"
         },
         "reference" : "ChIJdcPzzfUeoFMRI9nmSKRBlvM",
         "scope" : "GOOGLE",
         "types" : [ "gas_station", "point_of_interest", "establishment" ],
         "vicinity" : "906 111 Street Northwest, Edmonton"
      },
      {
         "geometry" : {
            "location" : {
               "lat" : 53.42436600000001,
               "lng" : -113.517576
            },
            "viewport" : {
               "northeast" : {
                  "lat" : 53.4259002802915,
                  "lng" : -113.5162263197085
               },
               "southwest" : {
                  "lat" : 53.4232023197085,
                  "lng" : -113.5189242802915
               }
            }
         },
         "icon" : "https://maps.gstatic.com/mapfiles/place_api/icons/gas_station-71.png",
         "id" : "08f6aac2c9e8cdb49ac89feb29ff54b782f5218f",
         "name" : "ESSO 7-Eleven 37813",
         "opening_hours" : {
            "open_now" : true
         },
         "photos" : [
            {
               "height" : 2448,
               "html_attributions" : [
                  "\u003ca href=\"https://maps.google.com/maps/contrib/117534506850508434501\"\u003eSandeep Goraya\u003c/a\u003e"
               ],
               "photo_reference" : "CmRaAAAA6ArIL3qHQ6L439Y7o-8mO3u4E_z1w3cD9JRDoDQSFmQ5Vb3M_c8ck2u0BJAINJlpXN0b5cVUug9mHqMWIXmXqr07Jk83sMjjHGN5M-T1mFB6PsdxJOA7FfyCQ_10X30KEhAU0KxiLSFIWf7afYCWCpNnGhQs5oKOTqD48ykY5qEEzWFeyhPmIA",
               "width" : 3264
            }
         ],
         "place_id" : "ChIJuQ2bRmMeoFMRb_NBQqouBBU",
         "plus_code" : {
            "compound_code" : "CFFJ+PX Edmonton, Alberta, Canada",
            "global_code" : "9558CFFJ+PX"
         },
         "rating" : 3.7,
         "reference" : "ChIJuQ2bRmMeoFMRb_NBQqouBBU",
         "scope" : "GOOGLE",
         "types" : [ "gas_station", "point_of_interest", "establishment" ],
         "user_ratings_total" : 95,
         "vicinity" : "11103 Ellerslie Road Southwest, Edmonton"
      },
      {
         "geometry" : {
            "location" : {
               "lat" : 53.42478000000001,
               "lng" : -113.51679
            },
            "viewport" : {
               "northeast" : {
                  "lat" : 53.4261158802915,
                  "lng" : -113.5154411697085
               },
               "southwest" : {
                  "lat" : 53.4234179197085,
                  "lng" : -113.5181391302915
               }
            }
         },
         "icon" : "https://maps.gstatic.com/mapfiles/place_api/icons/gas_station-71.png",
         "id" : "03c11891738cee43dab5bacbb4071a4d7dc71a7e",
         "name" : "Esso",
         "place_id" : "ChIJoVnARmMeoFMRAk2EMtFRlBU",
         "plus_code" : {
            "compound_code" : "CFFM+W7 Edmonton, Alberta, Canada",
            "global_code" : "9558CFFM+W7"
         },
         "reference" : "ChIJoVnARmMeoFMRAk2EMtFRlBU",
         "scope" : "GOOGLE",
         "types" : [ "gas_station", "point_of_interest", "establishment" ],
         "vicinity" : "11103 Ellerslie Road Southwest, Edmonton"
      },
      {
         "geometry" : {
            "location" : {
               "lat" : 53.4243315,
               "lng" : -113.5152733
            },
            "viewport" : {
               "northeast" : {
                  "lat" : 53.42561013029149,
                  "lng" : -113.5139270197085
               },
               "southwest" : {
                  "lat" : 53.4229121697085,
                  "lng" : -113.5166249802915
               }
            }
         },
         "icon" : "https://maps.gstatic.com/mapfiles/place_api/icons/gas_station-71.png",
         "id" : "765fb09fdc690f33bd0094075363b44e6834482f",
         "name" : "Petro-Canada",
         "opening_hours" : {
            "open_now" : true
         },
         "photos" : [
            {
               "height" : 720,
               "html_attributions" : [
                  "\u003ca href=\"https://maps.google.com/maps/contrib/109213930895157002939\"\u003ePetro-Canada\u003c/a\u003e"
               ],
               "photo_reference" : "CmRaAAAAdYV2W3-akyVBh4OupyzDHbI4swdwCOtfJvTUysX98bE7PyXa8Jkewa1605q_1e3N1I6PCGbkcHqGYGo5k03_G95nXQwXYJUcTTixkm9ljFhkvZl2DqkrciqE47ouB0DfEhBB94OqWiCz2A7dSBgyyIzpGhTViy_5YBZYxRSxFHmlpU1spnX7lQ",
               "width" : 720
            }
         ],
         "place_id" : "ChIJE2WQMGMeoFMR77HHUO7fDbs",
         "plus_code" : {
            "compound_code" : "CFFM+PV Edmonton, Alberta, Canada",
            "global_code" : "9558CFFM+PV"
         },
         "rating" : 3.9,
         "reference" : "ChIJE2WQMGMeoFMR77HHUO7fDbs",
         "scope" : "GOOGLE",
         "types" : [
            "gas_station",
            "convenience_store",
            "food",
            "point_of_interest",
            "store",
            "establishment"
         ],
         "user_ratings_total" : 79,
         "vicinity" : "11061 Ellerslie Road Southwest, Edmonton"
      },
      {
         "geometry" : {
            "location" : {
               "lat" : 53.45356659999999,
               "lng" : -113.5125465
            },
            "viewport" : {
               "northeast" : {
                  "lat" : 53.4549123802915,
                  "lng" : -113.5111377697085
               },
               "southwest" : {
                  "lat" : 53.4522144197085,
                  "lng" : -113.5138357302915
               }
            }
         },
         "icon" : "https://maps.gstatic.com/mapfiles/place_api/icons/gas_station-71.png",
         "id" : "6e3768551905fa0328453e6b14ad3129ed2c1337",
         "name" : "Shell",
         "opening_hours" : {
            "open_now" : true
         },
         "photos" : [
            {
               "height" : 2322,
               "html_attributions" : [
                  "\u003ca href=\"https://maps.google.com/maps/contrib/111660103354182818127\"\u003eAl Marediya\u003c/a\u003e"
               ],
               "photo_reference" : "CmRZAAAAOV1BlJ3YIsq2tLYlonjN5-gOSbeLJPpDyZe2UBdtZPpVcOpwiSBG2OW_m66tW95ON-4FKGWzygFMOs8BZE0QPHpMHLvqrpm7dQfwO3t9hr5tknoxkN_LlJmH-Zkt8Cq9EhAzXeyi6riaWwsvoj4wusFcGhSJX0zJKietcVC75Fk09-VrqCRTrA",
               "width" : 4128
            }
         ],
         "place_id" : "ChIJXbQUe-MeoFMRAW-R0G7CVPw",
         "plus_code" : {
            "compound_code" : "FF3P+CX Edmonton, Alberta, Canada",
            "global_code" : "9558FF3P+CX"
         },
         "price_level" : 2,
         "rating" : 3.4,
         "reference" : "ChIJXbQUe-MeoFMRAW-R0G7CVPw",
         "scope" : "GOOGLE",
         "types" : [
            "gas_station",
            "atm",
            "convenience_store",
            "finance",
            "food",
            "point_of_interest",
            "store",
            "establishment"
         ],
         "user_ratings_total" : 32,
         "vicinity" : "2203 110 Street Northwest, Edmonton"
      },
      {
         "geometry" : {
            "location" : {
               "lat" : 53.4545156,
               "lng" : -113.5126962
            },
            "viewport" : {
               "northeast" : {
                  "lat" : 53.45597468029149,
                  "lng" : -113.5113535697085
               },
               "southwest" : {
                  "lat" : 53.45327671970849,
                  "lng" : -113.5140515302915
               }
            }
         },
         "icon" : "https://maps.gstatic.com/mapfiles/place_api/icons/gas_station-71.png",
         "id" : "7d1f051b4309961d8dd912147815a98167a698ae",
         "name" : "Safeway Gas Bar",
         "opening_hours" : {
            "open_now" : true
         },
         "photos" : [
            {
               "height" : 2988,
               "html_attributions" : [
                  "\u003ca href=\"https://maps.google.com/maps/contrib/108056308214657461425\"\u003eJake Hammell\u003c/a\u003e"
               ],
               "photo_reference" : "CmRaAAAAKaMgn7N16YUYqEW2FaHwL10NTYYk3XgznEfXsPmpyv00HsJk-dsrTHU2tohB-bmVLPzyrxByZOGCFfrwq__avlJSfoss6fNrVwx_24x75nJkbRxViwAPH0PxkPKGAixzEhAm8o3QdVgqiM1QDM68DWkqGhScEWFDxgb-14h_Y-kWmqEy_VDrqw",
               "width" : 5312
            }
         ],
         "place_id" : "ChIJd3vOn-MeoFMREeOY3SQXE8E",
         "plus_code" : {
            "compound_code" : "FF3P+RW Edmonton, Alberta, Canada",
            "global_code" : "9558FF3P+RW"
         },
         "rating" : 3.5,
         "reference" : "ChIJd3vOn-MeoFMREeOY3SQXE8E",
         "scope" : "GOOGLE",
         "types" : [ "gas_station", "point_of_interest", "establishment" ],
         "user_ratings_total" : 21,
         "vicinity" : "10960 23 Avenue Northwest, Edmonton"
      }
   ],
   "status" : "OK"
}
