{
   "html_attributions" : [],
   "results" : [
      {
         "geometry" : {
            "location" : {
               "lat" : 53.628245,
               "lng" : -113.4856978
            },
            "viewport" : {
               "northeast" : {
                  "lat" : 53.6298282802915,
                  "lng" : -113.4843305697085
               },
               "southwest" : {
                  "lat" : 53.6271303197085,
                  "lng" : -113.4870285302915
               }
            }
         },
         "icon" : "https://maps.gstatic.com/mapfiles/place_api/icons/generic_business-71.png",
         "id" : "79b320a2a2970ab5f3577407a7e76b777c8b47b8",
         "name" : "Hughes",
         "opening_hours" : {
            "open_now" : true
         },
         "photos" : [
            {
               "height" : 4032,
               "html_attributions" : [
                  "\u003ca href=\"https://maps.google.com/maps/contrib/106804562157928407776/photos\"\u003ePalahitskyi Mykhailo\u003c/a\u003e"
               ],
               "photo_reference" : "CmRaAAAAMTyPXYWxAnyl9H98fFctjTOhLZSZ2GkQ2FDG--fyN4aNKm2sfOUaqN6CwmnVCZffkHrbsYxdw_bFARv2AYhRniCySYOV5QJJfBW41NkNsn08ri9I60MkuhyiHU1qNJMKEhBJOV2tf632xYNIm7ZUylsDGhSj4vEBdQYL7UhRzdzBOQR_h4_eCw",
               "width" : 3024
            }
         ],
         "place_id" : "ChIJJ5LGa8YkoFMRbel_AgqVPgw",
         "plus_code" : {
            "compound_code" : "JGH7+7P Edmonton, Alberta, Canada",
            "global_code" : "9558JGH7+7P"
         },
         "rating" : 4,
         "reference" : "CmRRAAAAE3XAOlpNCh0ekeZ2srnbUzDPhisaaHk5iW8X5F5qbrlJIue_nvR8VWY6EaVFwLXDEd4IaenQH1-WtsxYs7w-rFpukX4IGw37lN3OzmPaSwxDKjzne6XNRLhMyxoG3LeSEhAfwyNAlxF4mUYG0Sg2IA5AGhQQl8rf6pLtPI-SNGJVTwVobXb9aA",
         "scope" : "GOOGLE",
         "types" : [ "car_wash", "gas_station", "point_of_interest", "establishment" ],
         "vicinity" : "9551 167 Avenue, Edmonton"
      },
      {
         "geometry" : {
            "location" : {
               "lat" : 53.6211298,
               "lng" : -113.4682063
            },
            "viewport" : {
               "northeast" : {
                  "lat" : 53.6223105802915,
                  "lng" : -113.4668471697085
               },
               "southwest" : {
                  "lat" : 53.6196126197085,
                  "lng" : -113.4695451302915
               }
            }
         },
         "icon" : "https://maps.gstatic.com/mapfiles/place_api/icons/shopping-71.png",
         "id" : "9a8a1ec59368b47814bf353cf7bcb48326bbf6da",
         "name" : "7-Eleven",
         "opening_hours" : {
            "open_now" : true
         },
         "photos" : [
            {
               "height" : 720,
               "html_attributions" : [
                  "\u003ca href=\"https://maps.google.com/maps/contrib/112000279657034714372/photos\"\u003e7-Eleven\u003c/a\u003e"
               ],
               "photo_reference" : "CmRaAAAAvtCBePuFxbltfmeSYJ_9Fk8GmVb5LBI_PPr--gG7Cq4YfpenHZlxVGWLPilJ2_CHFiC09Ytr38DpeT-Twudb8y58XbL2eaplgzGnrVeJCg0gEo4RJ0c_B7z8jSMU5MBKEhAQWrovB3gXAHL50paatKECGhTcGxNBCsRkwo16qnXdh4VDpI7-Xg",
               "width" : 1280
            }
         ],
         "place_id" : "ChIJ61qzxLMkoFMRy5HfKMS4qs0",
         "plus_code" : {
            "compound_code" : "JGCJ+FP Edmonton, Alberta, Canada",
            "global_code" : "9558JGCJ+FP"
         },
         "rating" : 3.3,
         "reference" : "CmRSAAAA-Mq37G_XZZd-SMWnsunaot40-gfxyuDdl4CFt67A0_RkShr7SrZdj3lC_s-Wd2SDc33fWeorM3jAP6HBNKjhNKssAlT2pkTrBdQP3gIxNqYAY3fdOwPpdP9ISqlHDbdUEhCkkd6KJuSO0Dj-t92jem9mGhRQFwqDDBWieO7GKvLmGFvXtf3GRA",
         "scope" : "GOOGLE",
         "types" : [
            "convenience_store",
            "gas_station",
            "store",
            "food",
            "point_of_interest",
            "establishment"
         ],
         "vicinity" : "8210 160 Avenue Northwest, Edmonton"
      },
      {
         "geometry" : {
            "location" : {
               "lat" : 53.6389548,
               "lng" : -113.493171
            },
            "viewport" : {
               "northeast" : {
                  "lat" : 53.6402973802915,
                  "lng" : -113.4912687697085
               },
               "southwest" : {
                  "lat" : 53.6375994197085,
                  "lng" : -113.4939667302915
               }
            }
         },
         "icon" : "https://maps.gstatic.com/mapfiles/place_api/icons/shopping-71.png",
         "id" : "db41f3613e7625bf6abf74cfdfb78fd4c3f93832",
         "name" : "7-Eleven",
         "opening_hours" : {
            "open_now" : true
         },
         "photos" : [
            {
               "height" : 720,
               "html_attributions" : [
                  "\u003ca href=\"https://maps.google.com/maps/contrib/115733561434214412689/photos\"\u003e7-Eleven\u003c/a\u003e"
               ],
               "photo_reference" : "CmRaAAAAAy05unaw3Zn1wxN-UZ13k-ZsPPKSIZZDjjRs_J0qSTyfFlW7xmymuhMNGACS_JNaL458gD_MNYD-z0Z8TKK-D24CFChPYsGQ8TasXTqD9pz0B_ktc4tCeFKfc7odb9JZEhCrjOnhGsClU3NxMIOaIgjZGhQE-bW8Ug3izuECN5awdgMf9w-yQQ",
               "width" : 1280
            }
         ],
         "place_id" : "ChIJeWyX49AkoFMRM4rrN70DJgw",
         "plus_code" : {
            "compound_code" : "JGQ4+HP Edmonton, Alberta, Canada",
            "global_code" : "9558JGQ4+HP"
         },
         "rating" : 3.9,
         "reference" : "CmRRAAAAUQFvLC64pEETyqVvkffP21kswO_3Bu5kh2haPpjIUudr5QRvUDiQg3HfiqoLUA2VkB1d3uu-fQ1iZCFn9Mb_HK6p4XzLpH5fe8uTXJldZ1YVWjcVB7uDVfwZZBJDHoN6EhCkh1ypouvnWNmYEJEoTiKXGhQ9zRvGkI-3uQMXoqQGSaDKPH8uZg",
         "scope" : "GOOGLE",
         "types" : [
            "convenience_store",
            "gas_station",
            "store",
            "food",
            "point_of_interest",
            "establishment"
         ],
         "vicinity" : "17604 97 Street Northwest, Edmonton"
      },
      {
         "geometry" : {
            "location" : {
               "lat" : 53.62933689999999,
               "lng" : -113.460385
            },
            "viewport" : {
               "northeast" : {
                  "lat" : 53.63068038029149,
                  "lng" : -113.4587025197085
               },
               "southwest" : {
                  "lat" : 53.62798241970849,
                  "lng" : -113.4614004802915
               }
            }
         },
         "icon" : "https://maps.gstatic.com/mapfiles/place_api/icons/shopping-71.png",
         "id" : "44a3e24573e903ed1a0536719f5a9802e0b140bb",
         "name" : "7-Eleven",
         "opening_hours" : {
            "open_now" : true
         },
         "photos" : [
            {
               "height" : 720,
               "html_attributions" : [
                  "\u003ca href=\"https://maps.google.com/maps/contrib/102003789368850416017/photos\"\u003e7-Eleven\u003c/a\u003e"
               ],
               "photo_reference" : "CmRaAAAADkxjciljcZEQltg4XcSDG7T55bRBzrI_oYufPa5-ODoUqpHZnKY2o6XRM7YBXEt9vWGO19uCPCWqGPJRkMxIcm6m0GaHc518OGlYnOWjQSKFAigRFkH38NwpoodFkxATEhBLJo1yrQxQcOo4xtAmInXoGhS72t46vYN9GlxhyswWuknsRDF84Q",
               "width" : 1280
            }
         ],
         "place_id" : "ChIJEf5lGEo7oFMRF3jPBtE9-lc",
         "plus_code" : {
            "compound_code" : "JGHQ+PR Edmonton, Alberta, Canada",
            "global_code" : "9558JGHQ+PR"
         },
         "rating" : 2.9,
         "reference" : "CmRRAAAAFYdnI8g6tg1IJV96vKiq1rq25zAT4sV_86FWdnFL3b1YeeNf4bUR-x0g9uqRoFZmL4riYBBC0ylkqB5Aew8BpeUON9PChbLz3Iidqklw7ke4t2yjEGTLMoxG33YgPbi4EhDBEUPvada3oXHiV139BzcoGhT4v0PrmUyLzX_toU3khu57zTppyw",
         "scope" : "GOOGLE",
         "types" : [
            "convenience_store",
            "gas_station",
            "store",
            "food",
            "point_of_interest",
            "establishment"
         ],
         "vicinity" : "16720 76 Street Northwest, Edmonton"
      },
      {
         "geometry" : {
            "location" : {
               "lat" : 53.62940010000001,
               "lng" : -113.4974028
            },
            "viewport" : {
               "northeast" : {
                  "lat" : 53.6307532802915,
                  "lng" : -113.4965711697085
               },
               "southwest" : {
                  "lat" : 53.6280553197085,
                  "lng" : -113.4992691302915
               }
            }
         },
         "icon" : "https://maps.gstatic.com/mapfiles/place_api/icons/shopping-71.png",
         "id" : "ed59b31f9b46e7ede90694c90763d84f6bb9028b",
         "name" : "7-Eleven",
         "opening_hours" : {
            "open_now" : true
         },
         "photos" : [
            {
               "height" : 720,
               "html_attributions" : [
                  "\u003ca href=\"https://maps.google.com/maps/contrib/101413463172539307347/photos\"\u003e7-Eleven\u003c/a\u003e"
               ],
               "photo_reference" : "CmRaAAAAT6ZTWp1NC5q2arIQ80w28_820_gIbWMMVIBsOF_i_aufforWztspqF2v_9NiM9MDrOHxU5S6wyn9esc2j0TSkEea8svL5pqaP3rlV7LJ_B3czF9ryIGoGtmX8rHczs7HEhAjHJLUtOYZVeOk6NMV7XE1GhRul12lrAJhRoVx0XU48gx7gZeM3Q",
               "width" : 1280
            }
         ],
         "place_id" : "ChIJkRno7sMkoFMROWlenhWqOVM",
         "plus_code" : {
            "compound_code" : "JGH3+Q2 Edmonton, Alberta, Canada",
            "global_code" : "9558JGH3+Q2"
         },
         "rating" : 3.3,
         "reference" : "CmRRAAAAEPyqFw17uak0hZZX3ZFEvy8dqHBKfBPoF_uKODsmqSwjrH4Q_hG3eyURW2TjKc4nP1ZhICHZDoEvqD_ibvfDa0-FRuIvQnkausr7zXGf8ie1i9EgIuRioaeswc42yGwGEhCzHtSBkpT0LGal5_wxZPi6GhTu3QtM7cBSpwlGG5DRzRd5qVIj8Q",
         "scope" : "GOOGLE",
         "types" : [
            "convenience_store",
            "gas_station",
            "store",
            "food",
            "point_of_interest",
            "establishment"
         ],
         "vicinity" : "16703 100 Street Northwest, Edmonton"
      },
      {
         "geometry" : {
            "location" : {
               "lat" : 53.6291805,
               "lng" : -113.4808635
            },
            "viewport" : {
               "northeast" : {
                  "lat" : 53.63052968029149,
                  "lng" : -113.4798575697085
               },
               "southwest" : {
                  "lat" : 53.62783171970849,
                  "lng" : -113.4825555302915
               }
            }
         },
         "icon" : "https://maps.gstatic.com/mapfiles/place_api/icons/generic_business-71.png",
         "id" : "663a123a2b1678ef7fc9c157364e7ac686187a5d",
         "name" : "Mac's",
         "opening_hours" : {
            "open_now" : true
         },
         "place_id" : "ChIJv9V2P8kkoFMRo4KYdPclalw",
         "plus_code" : {
            "compound_code" : "JGH9+MM Edmonton, Alberta, Canada",
            "global_code" : "9558JGH9+MM"
         },
         "rating" : 3.7,
         "reference" : "CmRRAAAAq8Nq9KauiJpr0iPib8thZN3CvsBrEv2-8GdBtKTOX9yl1v4OU7bNjCPck9V3uwLQfwkEuuHV39N_rMpI0E4dVxT3-DBJmDjbjXmvCb-k8mwGLeHyadROAitAbpu0Z0YfEhCNKc9K0kZWCNIT7yq_n61nGhSgKgjNzybRxIk3GRgqkX-7WimEMw",
         "scope" : "GOOGLE",
         "types" : [
            "atm",
            "cafe",
            "gas_station",
            "finance",
            "store",
            "food",
            "point_of_interest",
            "establishment"
         ],
         "vicinity" : "16741 91 Street Northwest, Edmonton"
      },
      {
         "geometry" : {
            "location" : {
               "lat" : 53.6291913,
               "lng" : -113.4811317
            },
            "viewport" : {
               "northeast" : {
                  "lat" : 53.6305404302915,
                  "lng" : -113.4799916697085
               },
               "southwest" : {
                  "lat" : 53.6278424697085,
                  "lng" : -113.4826896302915
               }
            }
         },
         "icon" : "https://maps.gstatic.com/mapfiles/place_api/icons/gas_station-71.png",
         "id" : "5bb0f7e249a04f99976dbfec60ad0c80a1c6211a",
         "name" : "Esso",
         "opening_hours" : {
            "open_now" : true
         },
         "place_id" : "ChIJTxzIDskkoFMRaljLTvxGhLA",
         "plus_code" : {
            "compound_code" : "JGH9+MG Edmonton, Alberta, Canada",
            "global_code" : "9558JGH9+MG"
         },
         "rating" : 3.6,
         "reference" : "CmRSAAAAyvZNObWKBth29RAPv5BP9fOW0KIIaJdF0MAPIF1tD8hTArxaMteesEktB--93jJ92BW0aGF62kFZWvXKalDeSo5EwDH3KGp2-YNTzZJTRu6jS1MJoRrIOhTQqjne8Oo-EhAdsCqbd3hOE-UsnF0MUX7tGhRijhUFJq1E027EToT_d5gLHKyqTw",
         "scope" : "GOOGLE",
         "types" : [ "gas_station", "point_of_interest", "establishment" ],
         "vicinity" : "16791 91 Street Northwest, Edmonton"
      },
      {
         "geometry" : {
            "location" : {
               "lat" : 53.625402,
               "lng" : -113.491148
            },
            "viewport" : {
               "northeast" : {
                  "lat" : 53.6267510302915,
                  "lng" : -113.4901081697085
               },
               "southwest" : {
                  "lat" : 53.6240530697085,
                  "lng" : -113.4928061302915
               }
            }
         },
         "icon" : "https://maps.gstatic.com/mapfiles/place_api/icons/gas_station-71.png",
         "id" : "a02243fdf545aeb509ea55f07a7f2fbad2732230",
         "name" : "Petro-Canada",
         "opening_hours" : {
            "open_now" : true
         },
         "photos" : [
            {
               "height" : 1920,
               "html_attributions" : [
                  "\u003ca href=\"https://maps.google.com/maps/contrib/110746927392327489101/photos\"\u003eMichael Anderson\u003c/a\u003e"
               ],
               "photo_reference" : "CmRaAAAAwtyr-QyelaeLkcfLaOdBsjKW67s7QtczP-OiTGm6lcQpT93gumHGU1-HmIHCZ1eeUItEgE0pcxSs4wCqkbJ8tiLYuj--quSbXWGqrCadKdlwyhvU2nE8J1mXrQCpXNXoEhBq-neQrh-qgOUYRzWXKemAGhSt4w6irnQSJBgkIabiJ60ZnTPANA",
               "width" : 1080
            }
         ],
         "place_id" : "ChIJRRBFVVVVVQURxxHQwzc4EC0",
         "plus_code" : {
            "compound_code" : "JGG5+5G Edmonton, Alberta, Canada",
            "global_code" : "9558JGG5+5G"
         },
         "rating" : 4.1,
         "reference" : "CmRRAAAA9MKhi09KrFy0Q3lUoIUANP_cq08tCy2kH0iWB7GR7vQs_SyomUqMkoWikh3PvJVNQKalP7fCEfVVh8_PTvvmivJat3wa8FgF2H4CFPk55k2pwWGH8_xK2FnQTZmN-TcoEhCkihCWQEIWGPcP-ApcVJ8QGhScdSZ8F9R-IWkFuh2ZTRs_D29Tkw",
         "scope" : "GOOGLE",
         "types" : [ "gas_station", "point_of_interest", "establishment" ],
         "vicinity" : "16435 97 Street Northwest, Edmonton"
      },
      {
         "geometry" : {
            "location" : {
               "lat" : 53.6216392,
               "lng" : -113.4907371
            },
            "viewport" : {
               "northeast" : {
                  "lat" : 53.6228284802915,
                  "lng" : -113.4893832697085
               },
               "southwest" : {
                  "lat" : 53.6201305197085,
                  "lng" : -113.4920812302915
               }
            }
         },
         "icon" : "https://maps.gstatic.com/mapfiles/place_api/icons/gas_station-71.png",
         "id" : "728e0b0ca7ad1af1d7cccd4e7176015b2406def2",
         "name" : "Fas Gas Plus",
         "opening_hours" : {
            "open_now" : true
         },
         "photos" : [
            {
               "height" : 720,
               "html_attributions" : [
                  "\u003ca href=\"https://maps.google.com/maps/contrib/118308993840070597119/photos\"\u003eFas Gas Plus\u003c/a\u003e"
               ],
               "photo_reference" : "CmRaAAAAKytOA4K7TKjAKRFbSYG9seFQTkHcDqLG4qUe8aB89PI71GVJS0pB5Zd7BNKAh7Z4eYn8DrANw-uXs2rNzsLNdVIR0TbisAnt8v9X2nC0vafDjPUNQjwhqRBKSp_MOOrlEhCZfXX4QCQ9KOMQDkiEqCSfGhQ_9gf6Ibm4q0nDViE8oHbuDj0nzA",
               "width" : 720
            }
         ],
         "place_id" : "ChIJabneLb8koFMRCWmVhVlRFVk",
         "plus_code" : {
            "compound_code" : "JGC5+MP Edmonton, Alberta, Canada",
            "global_code" : "9558JGC5+MP"
         },
         "rating" : 4.1,
         "reference" : "CmRRAAAAd875K_GfUARe9z-WMahgJkEYrADAWdWn9zA7SoVaGCoxmaMjTKPJdoyJfv6uNcpRl6FlN9-TGEHaZKN66Xbza5ltfi4ywXfHTZXcCxaQpVoNZfjE0viSCipeW5tRfC03EhCOQkGjXJI9YyR0pcLz_bcLGhSCMg9MmstBMfJBb5t_cED_UHFmTQ",
         "scope" : "GOOGLE",
         "types" : [
            "gas_station",
            "atm",
            "convenience_store",
            "finance",
            "store",
            "food",
            "point_of_interest",
            "establishment"
         ],
         "vicinity" : "9618 160 Avenue Northwest, Edmonton"
      },
      {
         "geometry" : {
            "location" : {
               "lat" : 53.6292453,
               "lng" : -113.4654261
            },
            "viewport" : {
               "northeast" : {
                  "lat" : 53.6303753302915,
                  "lng" : -113.4640801697085
               },
               "southwest" : {
                  "lat" : 53.6276773697085,
                  "lng" : -113.4667781302915
               }
            }
         },
         "icon" : "https://maps.gstatic.com/mapfiles/place_api/icons/gas_station-71.png",
         "id" : "3ee3135f3f970c3c679e016359418551ae497812",
         "name" : "Petro-Canada",
         "opening_hours" : {
            "open_now" : true
         },
         "photos" : [
            {
               "height" : 720,
               "html_attributions" : [
                  "\u003ca href=\"https://maps.google.com/maps/contrib/108903692046397772687/photos\"\u003ePetro-Canada\u003c/a\u003e"
               ],
               "photo_reference" : "CmRaAAAAFqw0obBjCQ8VArgGtjLsRJ3WduakLlWwxOrX5l1a0XhVebxaS2YWcx9V0y3VWA9anAF8zsGXvHHNf3B2ojJ8uyhHp9PLLNAMjAcUv5iLStAoAMTPXZEevO5JLsg2A7kbEhCClOisvMYXHc6g8aXjxrzrGhQTdN3f5XVPgBenpLfngJ-pwaMxiw",
               "width" : 720
            }
         ],
         "place_id" : "ChIJ8cjWYzU7oFMRoCVv1Sj3J1U",
         "plus_code" : {
            "compound_code" : "JGHM+MR Edmonton, Alberta, Canada",
            "global_code" : "9558JGHM+MR"
         },
         "rating" : 3.8,
         "reference" : "CmRRAAAAAThB0crtkLOC5ZXR2fjS0Wxx0iBgv4Ql_smp8ho16g5CXtlcsGwUf_TKfkyRPDFRdtZJBIsA5L9TYCVZIKhAEhBBtK3aOBc0tHKmpJBFG8RWyGDd_45ShNE04U3Oxu-5EhD_3uJO_lSP8sWYFHMBuxi4GhT5Zqq9jGOwCHd4u2_LqwoKEk_GyA",
         "scope" : "GOOGLE",
         "types" : [ "gas_station", "point_of_interest", "establishment" ],
         "vicinity" : "8030 167 Avenue Northwest, Edmonton"
      },
      {
         "geometry" : {
            "location" : {
               "lat" : 53.618845,
               "lng" : -113.501818
            },
            "viewport" : {
               "northeast" : {
                  "lat" : 53.6203002802915,
                  "lng" : -113.5005633697085
               },
               "southwest" : {
                  "lat" : 53.6176023197085,
                  "lng" : -113.5032613302915
               }
            }
         },
         "icon" : "https://maps.gstatic.com/mapfiles/place_api/icons/gas_station-71.png",
         "id" : "2ff1be031a220ad8cf51a45eca79ccdc01853740",
         "name" : "TEMPO, Tay's Food Store",
         "opening_hours" : {
            "open_now" : true
         },
         "photos" : [
            {
               "height" : 3328,
               "html_attributions" : [
                  "\u003ca href=\"https://maps.google.com/maps/contrib/102055007821516666557/photos\"\u003eKlad Alzobi\u003c/a\u003e"
               ],
               "photo_reference" : "CmRaAAAAnldgLcbnVa4yXlq6glQwweS1EnUcWSr4pyjxIDEpJmlyfiUN0l9Jpqo-lsUhPWnJjYyLnT-NljMNeMuz-KqC0OWcc-_6Ib7lj5mlzWEnhwiVvBzu8AQRU7Q1xs4eCfaCEhDh33RADBvDzhTFUgz7xXSwGhRhq4O3h6TBg4m-S9gogtedBcI2JQ",
               "width" : 1872
            }
         ],
         "place_id" : "ChIJM-08_pQkoFMR_hXnN-gIgag",
         "plus_code" : {
            "compound_code" : "JF9X+G7 Edmonton, Alberta, Canada",
            "global_code" : "9558JF9X+G7"
         },
         "rating" : 3.3,
         "reference" : "CmRSAAAAIrC-CCsGSFt_0w6URBladhX6WbPnKpqZTNRjmq5v4W58RcPn4zf13turgHU-kCeSM73AwPGNHfil1Z_lxuzicRSOtRM6AHHqJqqQHUAz_9Mt3gzhDtmqzlh47tegWNJcEhCPH7sTuolPRqI02SSQljyuGhQfEszArpu7wbbenTaw2Jqwx5yCGw",
         "scope" : "GOOGLE",
         "types" : [
            "gas_station",
            "convenience_store",
            "store",
            "food",
            "point_of_interest",
            "establishment"
         ],
         "vicinity" : "10415 158 Avenue Northwest, Edmonton"
      },
      {
         "geometry" : {
            "location" : {
               "lat" : 53.614372,
               "lng" : -113.490829
            },
            "viewport" : {
               "northeast" : {
                  "lat" : 53.6156064802915,
                  "lng" : -113.4894880697085
               },
               "southwest" : {
                  "lat" : 53.6129085197085,
                  "lng" : -113.4921860302915
               }
            }
         },
         "icon" : "https://maps.gstatic.com/mapfiles/place_api/icons/gas_station-71.png",
         "id" : "16244b5a6f01ce977ce2d515cb7831beab19d421",
         "name" : "Esso",
         "opening_hours" : {
            "open_now" : true
         },
         "photos" : [
            {
               "height" : 489,
               "html_attributions" : [
                  "\u003ca href=\"https://maps.google.com/maps/contrib/104851171257693385857/photos\"\u003ePULIKEN\u003c/a\u003e"
               ],
               "photo_reference" : "CmRaAAAAu8L7us6ZNTtRl8kw-qC0CaP1VzVY-ZLIldPSRGZ1JN0jyv9rgpai6mpymrj9sz8nKmaBOiRJesIJKXnJiAStm5FhlpmK0sKvFJqXd2wyMi09G2LmrkXoLT1OoMCTVCt3EhDuEc2t3Ywuygb92j4xr3qfGhQ2Grb_J4TMU2Yd5weENoOV9_Z8AQ",
               "width" : 843
            }
         ],
         "place_id" : "ChIJgfZda70koFMRjRuArTedcQw",
         "plus_code" : {
            "compound_code" : "JG75+PM Edmonton, Alberta, Canada",
            "global_code" : "9558JG75+PM"
         },
         "rating" : 3.5,
         "reference" : "CmRRAAAAy0Q30rKQLhIqHIlb-pFh3j15BULfkDXqxGTOu-1tyvHZUx5vbhEEPhzRck9dGXu1yvoSA2Y9OZuza66eI8huwIiLZFlr8802dKgbVkwODxdZERzpEDeInsR0WA9zgHQuEhDEHTdhqOxj0-AO1CHN41R8GhSekbOaxzI7aCrHffcvVva16J1QcQ",
         "scope" : "GOOGLE",
         "types" : [ "gas_station", "point_of_interest", "establishment" ],
         "vicinity" : "9628 153 Avenue Northwest, Edmonton"
      },
      {
         "geometry" : {
            "location" : {
               "lat" : 53.61453650000001,
               "lng" : -113.4908268
            },
            "viewport" : {
               "northeast" : {
                  "lat" : 53.6156888302915,
                  "lng" : -113.4894916197085
               },
               "southwest" : {
                  "lat" : 53.6129908697085,
                  "lng" : -113.4921895802915
               }
            }
         },
         "icon" : "https://maps.gstatic.com/mapfiles/place_api/icons/shopping-71.png",
         "id" : "d34337ec0993b04e191f5647df8ea089d663ca47",
         "name" : "7-Eleven",
         "opening_hours" : {
            "open_now" : true
         },
         "photos" : [
            {
               "height" : 720,
               "html_attributions" : [
                  "\u003ca href=\"https://maps.google.com/maps/contrib/100383389239405769011/photos\"\u003e7-Eleven\u003c/a\u003e"
               ],
               "photo_reference" : "CmRaAAAAk_8JKZienH-93BT3L9XKBMLnMg5GL-cPcCvkWfkeG9HADx41HIDJSoJ0Uf35VOgg0VfsHSb21GyWmlQyGgwwxAY8UD7LhaiDBdp5XvJnuESpJJClvz0N03ehbhOttm6cEhC_rm8N1YUd1YEgNh-rXteFGhRwC2fG2NY3SZ-lRhYO7YOfFcjebA",
               "width" : 1280
            }
         ],
         "place_id" : "ChIJyX9fbb0koFMR5f_RVRm3xQQ",
         "plus_code" : {
            "compound_code" : "JG75+RM Edmonton, Alberta, Canada",
            "global_code" : "9558JG75+RM"
         },
         "rating" : 4.5,
         "reference" : "CmRRAAAAYZHYmclFUI4guBCuBNPN3g_-FFyEcIXU9C-829KxYblmBMNBSPm8EcbSLfQCRNnyxbO9YNE5VHu7pB7lzi7FRqsUTEIGM1bLIDnGP-tLYNvnwnp1XcA_3pHnT3O40Fz2EhBSXZ6dpj1yymC4VmdsUnTDGhQjgzuUVa6UnhMzc2zTwx5JgmbouA",
         "scope" : "GOOGLE",
         "types" : [
            "convenience_store",
            "gas_station",
            "store",
            "food",
            "point_of_interest",
            "establishment"
         ],
         "vicinity" : "9628 153 Avenue Northwest, Edmonton"
      },
      {
         "geometry" : {
            "location" : {
               "lat" : 53.6143687,
               "lng" : -113.4937281
            },
            "viewport" : {
               "northeast" : {
                  "lat" : 53.6155958302915,
                  "lng" : -113.4923800197085
               },
               "southwest" : {
                  "lat" : 53.6128978697085,
                  "lng" : -113.4950779802915
               }
            }
         },
         "icon" : "https://maps.gstatic.com/mapfiles/place_api/icons/gas_station-71.png",
         "id" : "aefebcca9b8c3cd927af318e93680d4703b52d2a",
         "name" : "Shell",
         "opening_hours" : {
            "open_now" : true
         },
         "photos" : [
            {
               "height" : 280,
               "html_attributions" : [
                  "\u003ca href=\"https://maps.google.com/maps/contrib/110530322675614937150/photos\"\u003eShell\u003c/a\u003e"
               ],
               "photo_reference" : "CmRaAAAAP6PUj76DC16ySbfvgIL7MwQJh4mP9dIp3F2UgbNVwztIcK9zeNo7heveeGpw-pwZPMTTuwB4HnWBD-aaAJD0O2NW8T-DmKjjP5iicXnmEAiDXiYOMWnsnJPDs900QJc2EhDQGWFCdTzeTT3xGjHD3QRxGhQaP2Si09oh-NAzftdws54qUitE2g",
               "width" : 303
            }
         ],
         "place_id" : "ChIJXY4LzpckoFMRNT7oRDslvy0",
         "plus_code" : {
            "compound_code" : "JG74+PG Edmonton, Alberta, Canada",
            "global_code" : "9558JG74+PG"
         },
         "price_level" : 2,
         "rating" : 3.7,
         "reference" : "CmRRAAAAV-jadNE_t5cuNxxSPlX2P6dooWlJbUn9UqDLd8MTXPfCey3O0KS_-EmIepcpIIduiJvHOpeuCCbSCdj-xuWrsXFnxv4_ZC8txUwoHlwtLMRXBZy7vP6wY_e_2NzQEuflEhAHqPHM-ptzS79xfrs_Cn8DGhSGjf0_E9qusKU3Zb8aoPi4ena0aQ",
         "scope" : "GOOGLE",
         "types" : [
            "gas_station",
            "atm",
            "convenience_store",
            "car_wash",
            "finance",
            "store",
            "food",
            "point_of_interest",
            "establishment"
         ],
         "vicinity" : "9804 153 Avenue Northwest, Edmonton"
      },
      {
         "geometry" : {
            "location" : {
               "lat" : 53.6340519,
               "lng" : -113.5174288
            },
            "viewport" : {
               "northeast" : {
                  "lat" : 53.6350921802915,
                  "lng" : -113.5161139197085
               },
               "southwest" : {
                  "lat" : 53.6323942197085,
                  "lng" : -113.5188118802915
               }
            }
         },
         "icon" : "https://maps.gstatic.com/mapfiles/place_api/icons/shopping-71.png",
         "id" : "7f291e59e8b9442876a893dc7c446bdd014466dd",
         "name" : "7-Eleven",
         "opening_hours" : {
            "open_now" : true
         },
         "photos" : [
            {
               "height" : 720,
               "html_attributions" : [
                  "\u003ca href=\"https://maps.google.com/maps/contrib/117363271170345438423/photos\"\u003e7-Eleven\u003c/a\u003e"
               ],
               "photo_reference" : "CmRaAAAANjORhA0vPx2bPs1FhwXV-6ynzNoJBGzNryouR87XF61h0_VE2S8EFtURwmGBa2clMfsPZmO56GoSNITzMOzrzS1qWC8OcOD3sbTkGB1BVWINww3qLnsBeEG66famlZzqEhAaOTPQXxxRhSpYrqnePF6xGhQm4uTlcqrF-M9t-UrULIzr0ygX6A",
               "width" : 1280
            }
         ],
         "place_id" : "ChIJ95wykuYkoFMRJAlJ-XOraPM",
         "plus_code" : {
            "compound_code" : "JFMM+J2 Edmonton, Alberta, Canada",
            "global_code" : "9558JFMM+J2"
         },
         "rating" : 4.1,
         "reference" : "CmRSAAAAfqfnBeW1D5lJ6ISWY5QZBxMjTJ8hYZM4A4u_HoDffdXOH1qkQz9XFjMugt27RnxNz299m_9ttCNR5cDoxvIWZRzuKvyQP-GB4fGlQvikUYvFKoUwyOtTKs2396Yc4KGlEhDOw-IEva74_dJve1ILwTD0GhTkdfWyTnTFKM5T0KnaXv44jJy72Q",
         "scope" : "GOOGLE",
         "types" : [
            "convenience_store",
            "gas_station",
            "store",
            "food",
            "point_of_interest",
            "establishment"
         ],
         "vicinity" : "11220 171 Avenue Northwest, Edmonton"
      },
      {
         "geometry" : {
            "location" : {
               "lat" : 53.62766790000001,
               "lng" : -113.5082595
            },
            "viewport" : {
               "northeast" : {
                  "lat" : 53.6290168802915,
                  "lng" : -113.5069105197085
               },
               "southwest" : {
                  "lat" : 53.6263189197085,
                  "lng" : -113.5096084802915
               }
            }
         },
         "icon" : "https://maps.gstatic.com/mapfiles/place_api/icons/gas_station-71.png",
         "id" : "44e397d88d384a03b617bd6b4e87c45a8255d106",
         "name" : "WAYSAVE",
         "place_id" : "ChIJsQRbvOkkoFMRVRVESAP9RXo",
         "plus_code" : {
            "compound_code" : "JFHR+3M Edmonton, Alberta, Canada",
            "global_code" : "9558JFHR+3M"
         },
         "reference" : "CmRRAAAABDaDifg4MogqzzqoL84E8yenShXdoaa4GUISnlJeZYhX8Wp7X09XRzaCnyqsLB41uYKhSi5drq40_9GhA2wLRezYMaLPQ9EymQ-3Z3kiQ3Z_dBfwZpFAePwymcUB9wRcEhBRj4Yjlwcc47X3JwrEvDYpGhQKmSaby_yu7-bBwHb2lEfGWkarQg",
         "scope" : "GOOGLE",
         "types" : [ "gas_station", "point_of_interest", "establishment" ],
         "vicinity" : "209 10807 CASTLEDOWNS RD, Edmonton"
      },
      {
         "geometry" : {
            "location" : {
               "lat" : 53.6204585,
               "lng" : -113.5038052
            },
            "viewport" : {
               "northeast" : {
                  "lat" : 53.6218239302915,
                  "lng" : -113.5025439197085
               },
               "southwest" : {
                  "lat" : 53.6191259697085,
                  "lng" : -113.5052418802915
               }
            }
         },
         "icon" : "https://maps.gstatic.com/mapfiles/place_api/icons/gas_station-71.png",
         "id" : "ca1fc7be022cbff863f8853a74392f978dec7218",
         "name" : "Belvedere Station",
         "place_id" : "ChIJkf3-2ZQkoFMRuEmSPArlIQA",
         "plus_code" : {
            "compound_code" : "JFCW+5F Edmonton, Alberta, Canada",
            "global_code" : "9558JFCW+5F"
         },
         "reference" : "ClRQAAAAh-xpgVsCZza7ia3qDK5W3OXQ4yAqGeOBhntTSRXLhCkXqwonc1B9tTIdZtxukOxw8B8dHR1q_XV71oBCWSu06jGQ6U_Q4c5a4ihKiwsrDiESEB7doL58QSBNtzZ6YGVAlwsaFOg5Zqmra6Y5UnwLU9S7DgB-GuMp",
         "scope" : "GOOGLE",
         "types" : [ "gas_station", "point_of_interest", "establishment" ],
         "vicinity" : "87 Stirling Road Northwest, Edmonton"
      },
      {
         "geometry" : {
            "location" : {
               "lat" : 53.616395,
               "lng" : -113.4902749
            },
            "viewport" : {
               "northeast" : {
                  "lat" : 53.6177357302915,
                  "lng" : -113.489548
               },
               "southwest" : {
                  "lat" : 53.6150377697085,
                  "lng" : -113.4924556
               }
            }
         },
         "icon" : "https://maps.gstatic.com/mapfiles/place_api/icons/gas_station-71.png",
         "id" : "38fd071bb0641a23366ce48b0cd398d861324e0f",
         "name" : "Mobil",
         "opening_hours" : {
            "open_now" : true
         },
         "place_id" : "ChIJNxPXCW8loFMRwQblR_XMVmc",
         "plus_code" : {
            "compound_code" : "JG85+HV Edmonton, Alberta, Canada",
            "global_code" : "9558JG85+HV"
         },
         "reference" : "CmRRAAAA0W26z39kuCp7xeq0qxXLskpk_JuGFwiKv39FO60j87wjfaTsTWJycRLtJKITCEYQnbMUFUQdud6_YCaJXRa3syLCWK0Uovia1f6id_2-X78eeac04-Wpx-oR-IupvZIXEhBfzAoSngvh0W2tOXRgublFGhRWip7sso57qAMkNJW9wTfx6hKbGg",
         "scope" : "GOOGLE",
         "types" : [ "gas_station", "point_of_interest", "establishment" ],
         "vicinity" : "15505 97 Street Northwest, Edmonton"
      }
   ],
   "status" : "OK"
}
