[{"friday_close":"18:00","friday_open":"10:00","library":"Country Hills Library","location":{"type":"Point","coordinates":[-114.0675659,51.159462]},"location_1":{"type":"Point","coordinates":[-114.0675659,51.159462]},"location_1_address":"388 Country Hills Bv NE","monday_close":"21:00","monday_open":"10:00","phone_number":"403-260-2600","postal_code":"T3K 6E3","range":"946.979769899999951","saturday_close":"17:00","saturday_open":"10:00","square_feet":"18127","sunday_close":"17:00","sunday_open":"12:00","thursday_close":"21:00","thursday_open":"10:00","tuesday_close":"21:00","tuesday_open":"10:00","wednesday_close":"21:00","wednesday_open":"10:00"}]
