[{"latitude":"53.47615386619935","location":{"type":"Point","coordinates":[-113.596579820974,53.476212562304]},"longitude":"-113.59667534648857","name":"Kinross-Kerr Park","neighbourhood_id":"5350","neighbourhood_name":"Rhatigan Ridge","range":"250.332401470000008"}
,{"latitude":"53.475941046993455","location":{"type":"Point","coordinates":[-113.596634555078,53.476018288546]},"longitude":"-113.59657962884079","name":"Kinross-Kerr Park","neighbourhood_id":"5350","neighbourhood_name":"Rhatigan Ridge","range":"271.443912529999977"}]
